mathgeoalgebra/__init__.py
mathgeoalgebra/algebra.py
mathgeoalgebra/geometry.py
mathgeoalgebra/matrix.py
mathgeoalgebra-1.0.0.dist-info/METADATA
mathgeoalgebra-1.0.0.dist-info/WHEEL
mathgeoalgebra-1.0.0.dist-info/top_level.txt
mathgeoalgebra-1.0.0.dist-info/RECORD
